commonroad_dc/__init__.py
commonroad_dc/__version__.py
commonroad_dc/py.typed
commonroad_dc/pycrcc.cpython-313-x86_64-linux-gnu.so
commonroad_dc/pycrcc.pyi
commonroad_dc/boundary/__init__.py
commonroad_dc/boundary/boundary.py
commonroad_dc/boundary/construction.py
commonroad_dc/boundary/lanelet_bounds.py
commonroad_dc/boundary/rectangle_builder.py
commonroad_dc/boundary/scenario_bounds.py
commonroad_dc/boundary/triangle_builder.py
commonroad_dc/collision/__init__.py
commonroad_dc/collision/collision_detection/__init__.py
commonroad_dc/collision/collision_detection/minkowski_sum.py
commonroad_dc/collision/collision_detection/pycrcc_collision_dispatch.py
commonroad_dc/collision/collision_detection/scenario.py
commonroad_dc/collision/trajectory_queries/trajectory_queries.py
commonroad_dc/collision/trajectory_queries/trajectory_queries_specialized.py
commonroad_dc/collision/visualization/__init__.py
commonroad_dc/collision/visualization/drawing.py
commonroad_dc/costs/__init__.py
commonroad_dc/costs/evaluation.py
commonroad_dc/costs/partial_cost_functions.py
commonroad_dc/costs/route_matcher.py
commonroad_dc/feasibility/__init__.py
commonroad_dc/feasibility/feasibility_checker.py
commonroad_dc/feasibility/solution_checker.py
commonroad_dc/feasibility/vehicle_dynamics.py
commonroad_dc/geometry/__init__.py
commonroad_dc/geometry/geometry.py
commonroad_dc/geometry/lanelet_ccosy.py
commonroad_dc/geometry/util.py
commonroad_dc/pycrccosy/__init__.py
commonroad_drivability_checker-2025.3.1.dist-info/METADATA
commonroad_drivability_checker-2025.3.1.dist-info/WHEEL
commonroad_drivability_checker-2025.3.1.dist-info/RECORD
commonroad_drivability_checker-2025.3.1.dist-info/licenses/LICENSE.txt
