Metadata-Version: 2.1
Name: commonroad-drivability-checker
Version: 2025.3.1
Summary: Drivability checker for CommonRoad scenarios.
Author-Email: Cyber-Physical Systems Group - Technical University of Munich <commonroad@lists.lrz.de>
License: BSD 3-Clause License
Classifier: Programming Language :: C++
Classifier: Programming Language :: Python :: 3.10
Classifier: Programming Language :: Python :: 3.11
Classifier: Programming Language :: Python :: 3.12
Classifier: Programming Language :: Python :: 3.13
Classifier: License :: OSI Approved :: BSD License
Classifier: Operating System :: POSIX :: Linux
Classifier: Operating System :: MacOS
Project-URL: Homepage, https://commonroad.in.tum.de/tools/drivability-checker
Project-URL: Documentation, https://cps.pages.gitlab.lrz.de/commonroad-drivability-checker/
Project-URL: Source, https://github.com/CommonRoad/commonroad-drivability-checker
Requires-Python: <3.14,>=3.10
Requires-Dist: commonroad-io<2025.0,>=2023.1
Requires-Dist: commonroad-vehicle-models<4.0.0,>=3.0.0
Requires-Dist: numpy<3.0,>=1.20
Requires-Dist: scipy<2.0,>=1.7.0
Requires-Dist: polygon3<4.0.0,>=3.0.8
Requires-Dist: shapely<3.0.0,>=2.0.0
Requires-Dist: matplotlib<4.0.0,>=3.2.2
Provides-Extra: clcs
Requires-Dist: commonroad-clcs<2026.0.0,>=2025.1.0; extra == "clcs"
Provides-Extra: triangle
Requires-Dist: triangle>=20250106; extra == "triangle"
Provides-Extra: test
Requires-Dist: pytest>=5.3.2; extra == "test"
Provides-Extra: docs
Requires-Dist: sphinx_rtd_theme>=0.4.3; extra == "docs"
Requires-Dist: sphinx>=3.0.3; extra == "docs"
Requires-Dist: nbsphinx_link>=1.3.0; extra == "docs"
Requires-Dist: nbsphinx>=0.6.1; extra == "docs"
Requires-Dist: breathe>=4.18.0; extra == "docs"
Requires-Dist: ipython>=8.36.0; extra == "docs"
Requires-Dist: cmake<4.0,>=3.24; extra == "docs"
Provides-Extra: build
Requires-Dist: scikit-build-core~=0.11.0; extra == "build"
Requires-Dist: nanobind~=2.2.0; extra == "build"
Requires-Dist: pathspec>=0.12.1; extra == "build"
Requires-Dist: pyproject-metadata>=0.7.1; extra == "build"
Requires-Dist: typing_extensions~=4.12.2; extra == "build"
Requires-Dist: cmake<4.0,>=3.24; extra == "build"
